stock_learning_rabbitmq/AnalyserStub.py
stock_learning_rabbitmq/ApiScrapperStub.py
stock_learning_rabbitmq/ApiStub.py
stock_learning_rabbitmq/RabbitMQServer.py
stock_learning_rabbitmq/Stub.py
stock_learning_rabbitmq/WebScrappingStub.py
stock_learning_rabbitmq/__init__.py
stock_learning_rabbitmq-0.0.26.dist-info/LICENSE
stock_learning_rabbitmq-0.0.26.dist-info/METADATA
stock_learning_rabbitmq-0.0.26.dist-info/WHEEL
stock_learning_rabbitmq-0.0.26.dist-info/top_level.txt
stock_learning_rabbitmq-0.0.26.dist-info/RECORD
