Metadata-Version: 2.1
Name: stock-learning-rabbitmq
Version: 0.0.26
Summary: This is a package that includes all RabbitMQ handled messages by the stock-learning infrastructure
Home-page: UNKNOWN
License: UNKNOWN
Platform: UNKNOWN
Classifier: Programming Language :: Python :: 3
Classifier: License :: OSI Approved :: MIT License
Classifier: Operating System :: OS Independent
Requires-Python: >=3.6
